team_x_og/__init__.py
team_x_og/bot.py
team_x_og/cli.py
team_x_og/errors.py
team_x_og/handlers.py
team_x_og/inline.py
team_x_og/keyboard.py
team_x_og/media.py
team_x_og/plugins.py
team_x_og-0.1.0.dist-info/LICENSE
team_x_og-0.1.0.dist-info/METADATA
team_x_og-0.1.0.dist-info/WHEEL
team_x_og-0.1.0.dist-info/entry_points.txt
team_x_og-0.1.0.dist-info/top_level.txt
team_x_og-0.1.0.dist-info/RECORD
