Metadata-Version: 2.1
Name: team_x_og
Version: 0.1.0
Summary: A powerful and beginner-friendly Telegram bot library
Home-page: https://github.com/ARMAN01011
Author: Your Name
Author-email: armanhacker95@gmail.com
Classifier: Programming Language :: Python :: 3
Classifier: License :: OSI Approved :: MIT License
Classifier: Operating System :: OS Independent
Requires-Python: >=3.7
License-File: LICENSE
Requires-Dist: aiohttp>=3.8.0
Requires-Dist: click>=8.0.0
